LICENSE
README.md
setup.cfg
setup.py
alpypeopt/__init__.py
alpypeopt.egg-info/PKG-INFO
alpypeopt.egg-info/SOURCES.txt
alpypeopt.egg-info/dependency_links.txt
alpypeopt.egg-info/requires.txt
alpypeopt.egg-info/top_level.txt
alpypeopt/anylogic/__init__.py
alpypeopt/anylogic/model/__init__.py
alpypeopt/anylogic/model/connector.py
alpypeopt/anylogic/model/launcher.py
alpypeopt/wrapper/__init__.py
alpypeopt/wrapper/envs/__init__.py
alpypeopt/wrapper/envs/anylogic_env.py