Metadata-Version: 2.1
Name: alpypeopt
Version: 0.0.1
Summary: An open source library for connecting AnyLogic models with python-based sequential optimization packages
Home-page: https://github.com/MarcEscandell/ALPypeOpt
Author: Marc Escandell Mari
Author-email: marcescandellmari@gmail.com
License: Apache License, Version 2.0
Keywords: alpypeopt
Requires-Python: >=3.9
License-File: LICENSE
